pybk8500/__init__.py
pybk8500/__meta__.py
pybk8500/combine_csv.py
pybk8500/commands.py
pybk8500/field_types.py
pybk8500/parser.py
pybk8500/plot_csv.py
pybk8500/run_profile.py
pybk8500/send_cmd.py
pybk8500/utils.py
pybk8500/__pycache__/__init__.cpython-38.pyc
pybk8500/__pycache__/__meta__.cpython-38.pyc
pybk8500/__pycache__/combine_csv.cpython-38.pyc
pybk8500/__pycache__/commands.cpython-38.pyc
pybk8500/__pycache__/field_types.cpython-38.pyc
pybk8500/__pycache__/parser.cpython-38.pyc
pybk8500/__pycache__/plot_csv.cpython-38.pyc
pybk8500/__pycache__/run_profile.cpython-38.pyc
pybk8500/__pycache__/send_cmd.cpython-38.pyc
pybk8500/__pycache__/utils.cpython-38.pyc
pybk8500-1.2.0.dist-info/LICENSE
pybk8500-1.2.0.dist-info/METADATA
pybk8500-1.2.0.dist-info/WHEEL
pybk8500-1.2.0.dist-info/top_level.txt
pybk8500-1.2.0.dist-info/RECORD
