Metadata-Version: 2.1
Name: pybk8500
Version: 1.2.0
Summary: BK-8500-Electronic-Load python library
Home-page: https://github.com/justengel/pybk8500
Author: Justin Engel
Author-email: jtengel08@gmail.com
License: MIT
Download-URL: https://github.com/justengel/pybk8500/archive/v1.2.0.tar.gz
Keywords: BK8500 BK-8500 Electronic Load
Platform: any
Classifier: Programming Language :: Python
Classifier: Programming Language :: Python :: 3
Classifier: Operating System :: OS Independent
Requires-Dist: dynamicmethod (>=1.0.4)
Requires-Dist: bitflags (>=1.1.0)
Provides-Extra: all
Requires-Dist: pyserial (>=3.4) ; extra == 'all'
Requires-Dist: continuous-threading (>=2.0.0) ; extra == 'all'
Requires-Dist: matplotlib (>=3.3.2) ; extra == 'all'
Provides-Extra: plot
Requires-Dist: matplotlib (>=3.3.2) ; extra == 'plot'
Provides-Extra: serial
Requires-Dist: pyserial (>=3.4) ; extra == 'serial'
Requires-Dist: continuous-threading (>=2.0.0) ; extra == 'serial'
